hdfsbrowser/__init__.py
hdfsbrowser/_version.py
hdfsbrowser/serverextension.py
hdfsbrowser/labextension/build_log.json
hdfsbrowser/labextension/package.json
hdfsbrowser/labextension/static/lib_index_js.ce9bcabfe81acf9d4108.js
hdfsbrowser/labextension/static/lib_index_js.ce9bcabfe81acf9d4108.js.map
hdfsbrowser/labextension/static/remoteEntry.2cf760731238621b41a4.js
hdfsbrowser/labextension/static/remoteEntry.2cf760731238621b41a4.js.map
hdfsbrowser/labextension/static/style.js
hdfsbrowser/labextension/static/style_index_css.fbb252df4087bcfd2c30.js
hdfsbrowser/labextension/static/style_index_css.fbb252df4087bcfd2c30.js.map
hdfsbrowser/labextension/static/vendors-node_modules_css-loader_dist_runtime_api_js-node_modules_css-loader_dist_runtime_cssW-926fd9.84129c587653504fb052.js
hdfsbrowser/labextension/static/vendors-node_modules_css-loader_dist_runtime_api_js-node_modules_css-loader_dist_runtime_cssW-926fd9.84129c587653504fb052.js.map
hdfsbrowser/nbextension/extension.js
hdfsbrowser-1.1.1.data/data/etc/jupyter/jupyter_notebook_config.d/hdfsbrowser.json
hdfsbrowser-1.1.1.data/data/etc/jupyter/jupyter_server_config.d/hdfsbrowser.json
hdfsbrowser-1.1.1.data/data/share/jupyter/labextensions/@swan-cern/hdfsbrowser/build_log.json
hdfsbrowser-1.1.1.data/data/share/jupyter/labextensions/@swan-cern/hdfsbrowser/package.json
hdfsbrowser-1.1.1.data/data/share/jupyter/labextensions/@swan-cern/hdfsbrowser/static/lib_index_js.ce9bcabfe81acf9d4108.js
hdfsbrowser-1.1.1.data/data/share/jupyter/labextensions/@swan-cern/hdfsbrowser/static/lib_index_js.ce9bcabfe81acf9d4108.js.map
hdfsbrowser-1.1.1.data/data/share/jupyter/labextensions/@swan-cern/hdfsbrowser/static/remoteEntry.2cf760731238621b41a4.js
hdfsbrowser-1.1.1.data/data/share/jupyter/labextensions/@swan-cern/hdfsbrowser/static/remoteEntry.2cf760731238621b41a4.js.map
hdfsbrowser-1.1.1.data/data/share/jupyter/labextensions/@swan-cern/hdfsbrowser/static/style.js
hdfsbrowser-1.1.1.dist-info/METADATA
hdfsbrowser-1.1.1.dist-info/WHEEL
hdfsbrowser-1.1.1.dist-info/top_level.txt
hdfsbrowser-1.1.1.dist-info/RECORD
